sphinx_holoviz_theme/__init__.py
sphinx_holoviz_theme/_version.py
sphinx_holoviz_theme/layout.html
sphinx_holoviz_theme/search.html
sphinx_holoviz_theme/theme.conf
sphinx_holoviz_theme/includes/searchbox.html
sphinx_holoviz_theme/static/css/main.css_t
sphinx_holoviz_theme/static/images/favicon.ico
sphinx_holoviz_theme/static/images/logo.png
sphinx_holoviz_theme/static/js/main.js
sphinx_holoviz_theme-0.1.4.dist-info/LICENSE.txt
sphinx_holoviz_theme-0.1.4.dist-info/METADATA
sphinx_holoviz_theme-0.1.4.dist-info/WHEEL
sphinx_holoviz_theme-0.1.4.dist-info/entry_points.txt
sphinx_holoviz_theme-0.1.4.dist-info/top_level.txt
sphinx_holoviz_theme-0.1.4.dist-info/RECORD
