Metadata-Version: 2.1
Name: sphinx-holoviz-theme
Version: 0.1.4
Summary: Theme for building HoloViz sites; best when used with nbsite.
Home-page: https://github.com/pyviz-dev/sphinx_holoviz_theme
License: BSD-3
Platform: UNKNOWN
Requires-Python: >=2.7
Requires-Dist: sphinx
